poly_py_tools/__init__.py
poly_py_tools/config_writer.py
poly_py_tools/configure.py
poly_py_tools/csv_parser_config.py
poly_py_tools/device_configuration.py
poly_py_tools/polycom_config_writer.py
poly_py_tools/polycom_phone.py
poly_py_tools/provision.py
poly_py_tools/pw_strength_calculator.py
poly_py_tools/registration.py
poly_py_tools/sip_builder.py
poly_py_tools/sip_manager.py
poly_py_tools/sip_parser.py
poly_py_tools/template.py
poly_py_tools/validator.py
poly_py_tools-2.1.2.dist-info/LICENSE
poly_py_tools-2.1.2.dist-info/METADATA
poly_py_tools-2.1.2.dist-info/WHEEL
poly_py_tools-2.1.2.dist-info/top_level.txt
poly_py_tools-2.1.2.dist-info/RECORD
