Metadata-Version: 2.1
Name: poly-py-tools
Version: 2.1.2
Summary: A package for working with Asterisk and Polycom config files.
Home-page: https://github.com/mjmunger/PolyPyTools
Author: Michael Munger
Author-email: mj@hp.io
License: UNKNOWN
Platform: UNKNOWN
Classifier: Programming Language :: Python :: 3
Classifier: License :: OSI Approved :: MIT License
Classifier: Operating System :: OS Independent
Classifier: Topic :: System :: Systems Administration
Classifier: Topic :: Utilities
Classifier: Development Status :: 4 - Beta
Classifier: Environment :: Console
